bonsai_ai/__init__.py
bonsai_ai/aad.py
bonsai_ai/aria_writer.py
bonsai_ai/brain.py
bonsai_ai/brain_api.py
bonsai_ai/brain_controller.py
bonsai_ai/config.py
bonsai_ai/event.py
bonsai_ai/exceptions.py
bonsai_ai/inkling_factory.py
bonsai_ai/inkling_types.py
bonsai_ai/logger.py
bonsai_ai/predictor.py
bonsai_ai/simulator.py
bonsai_ai/simulator_connection.py
bonsai_ai/simulator_ws.py
bonsai_ai/token_cache.py
bonsai_ai/version.py
bonsai_ai/writer.py
bonsai_ai/_vendor/__init__.py
bonsai_ai/_vendor/product_insights/__init__.py
bonsai_ai/_vendor/product_insights/_type_hints.py
bonsai_ai/_vendor/product_insights/annotations.py
bonsai_ai/_vendor/product_insights/constants.py
bonsai_ai/_vendor/product_insights/context.py
bonsai_ai/_vendor/product_insights/debug.py
bonsai_ai/_vendor/product_insights/event_counter.py
bonsai_ai/_vendor/product_insights/event_properties.py
bonsai_ai/_vendor/product_insights/event_uploader.py
bonsai_ai/_vendor/product_insights/log_configuration.py
bonsai_ai/_vendor/product_insights/log_event_drop_reason.py
bonsai_ai/_vendor/product_insights/log_manager.py
bonsai_ai/_vendor/product_insights/log_manager_configuration.py
bonsai_ai/_vendor/product_insights/log_manager_resources.py
bonsai_ai/_vendor/product_insights/logger.py
bonsai_ai/_vendor/product_insights/opaque_logger.py
bonsai_ai/_vendor/product_insights/pi_schemas.py
bonsai_ai/_vendor/product_insights/pii_kind.py
bonsai_ai/_vendor/product_insights/poller.py
bonsai_ai/_vendor/product_insights/proxifier.py
bonsai_ai/_vendor/product_insights/serial_number.py
bonsai_ai/_vendor/product_insights/singletons.py
bonsai_ai/_vendor/product_insights/util.py
bonsai_ai/_vendor/product_insights/_lib/__init__.py
bonsai_ai/_vendor/product_insights/_lib/six.py
bonsai_ai/_vendor/product_insights/_lib/pybond/__init__.py
bonsai_ai/_vendor/product_insights/_lib/pybond/bond_field.py
bonsai_ai/_vendor/product_insights/_lib/pybond/encoders/__init__.py
bonsai_ai-2.2.8.dist-info/LICENSE.txt
bonsai_ai-2.2.8.dist-info/METADATA
bonsai_ai-2.2.8.dist-info/WHEEL
bonsai_ai-2.2.8.dist-info/top_level.txt
bonsai_ai-2.2.8.dist-info/RECORD
