Metadata-Version: 2.1
Name: bonsai-ai
Version: 2.2.8
Summary: Simulator interface library for Bonsai AI platform v2
Home-page: https://bons.ai
Author: Bonsai, Inc.
Author-email: opensource@bons.ai
License: BSD
Keywords: bonsai
Platform: UNKNOWN
Classifier: Development Status :: 4 - Beta
Classifier: Intended Audience :: Developers
Classifier: Topic :: Scientific/Engineering :: Artificial Intelligence
Classifier: License :: OSI Approved :: BSD License
Classifier: Programming Language :: Python :: 3.5
Classifier: Programming Language :: Python :: 3.6
Classifier: Natural Language :: English
Requires-Python: >=3.5
Requires-Dist: wheel (>=0.31.0)
Requires-Dist: protobuf (<4,>=3.0.0)
Requires-Dist: requests (>=2.11)
Requires-Dist: yarl (==1.2.0)
Requires-Dist: configparser (>=3.5.0)
Requires-Dist: async-timeout (==2.0.1)
Requires-Dist: aiohttp (==2.3.10)
Requires-Dist: msal (>=0.8.0)
